test_project_poetry_github/__init__.py
test_project_poetry_github-0.1.1.dist-info/WHEEL
test_project_poetry_github-0.1.1.dist-info/METADATA
test_project_poetry_github-0.1.1.dist-info/RECORD
