Metadata-Version: 2.1
Name: test-project-poetry-github
Version: 0.1.1
Summary: 
Author: Victor Silva
Author-email: victor.hos@gmail.com
Requires-Python: >=3.7,<4.0
Classifier: Programming Language :: Python :: 3
Classifier: Programming Language :: Python :: 3.7
Classifier: Programming Language :: Python :: 3.8
Requires-Dist: django (>=3.0.8,<4.0.0)
